<?xml version="1.0" encoding="UTF-8" ?>
<!DOCTYPE mapper PUBLIC "-//mybatis.org//DTD Mapper 3.0//EN" "http://mybatis.org/dtd/mybatis-3-mapper.dtd" >
<mapper namespace="com.victor.h5blog.dao.LeftMenuDao" >
  <resultMap id="BaseResultMap" type="com.victor.h5blog.entity.LeftMenu" >
    <id column="MENU_ID" property="id" jdbcType="BIGINT" />
    <result column="MENU_NAME" property="name" jdbcType="VARCHAR" />
    <result column="MENU_URL" property="url" jdbcType="VARCHAR" />
    <result column="MENU_ORDER" property="order" jdbcType="INTEGER" />
    <result column="MENU_ICO" property="ico" jdbcType="VARCHAR" />
    <result column="MENU_STATUS" property="status" jdbcType="BIT" />
    <result column="MENU_PARENT_ID" property="parentId" jdbcType="BIGINT" />
    <result column="MENU_KEY" property="key" jdbcType="VARCHAR" />
  </resultMap>
  <sql id="Example_Where_Clause" >
    <where >
      <foreach collection="oredCriteria" item="criteria" separator="or" >
        <if test="criteria.valid" >
          <trim prefix="(" suffix=")" prefixOverrides="and" >
            <foreach collection="criteria.criteria" item="criterion" >
              <choose >
                <when test="criterion.noValue" >
                  and ${criterion.condition}
                </when>
                <when test="criterion.singleValue" >
                  and ${criterion.condition} #{criterion.value}
                </when>
                <when test="criterion.betweenValue" >
                  and ${criterion.condition} #{criterion.value} and #{criterion.secondValue}
                </when>
                <when test="criterion.listValue" >
                  and ${criterion.condition}
                  <foreach collection="criterion.value" item="listItem" open="(" close=")" separator="," >
                    #{listItem}
                  </foreach>
                </when>
              </choose>
            </foreach>
          </trim>
        </if>
      </foreach>
    </where>
  </sql>
  <sql id="Update_By_Example_Where_Clause" >
    <where >
      <foreach collection="example.oredCriteria" item="criteria" separator="or" >
        <if test="criteria.valid" >
          <trim prefix="(" suffix=")" prefixOverrides="and" >
            <foreach collection="criteria.criteria" item="criterion" >
              <choose >
                <when test="criterion.noValue" >
                  and ${criterion.condition}
                </when>
                <when test="criterion.singleValue" >
                  and ${criterion.condition} #{criterion.value}
                </when>
                <when test="criterion.betweenValue" >
                  and ${criterion.condition} #{criterion.value} and #{criterion.secondValue}
                </when>
                <when test="criterion.listValue" >
                  and ${criterion.condition}
                  <foreach collection="criterion.value" item="listItem" open="(" close=")" separator="," >
                    #{listItem}
                  </foreach>
                </when>
              </choose>
            </foreach>
          </trim>
        </if>
      </foreach>
    </where>
  </sql>
  <sql id="Base_Column_List" >
    MENU_ID, MENU_NAME, MENU_URL, MENU_ORDER, MENU_ICO, MENU_STATUS, MENU_PARENT_ID, 
    MENU_KEY
  </sql>
  <select id="selectByExample" resultMap="BaseResultMap" parameterType="com.victor.h5blog.entity.LeftMenuExample" >
    select
    <if test="distinct" >
      distinct
    </if>
    'true' as QUERYID,
    <include refid="Base_Column_List" />
    from LEGOO_LEFT_MENU
    <if test="_parameter != null" >
      <include refid="Example_Where_Clause" />
    </if>
    <if test="orderByClause != null" >
      order by ${orderByClause}
    </if>
  </select>
  <select id="selectByPrimaryKey" resultMap="BaseResultMap" parameterType="java.lang.Long" >
    select 
    <include refid="Base_Column_List" />
    from LEGOO_LEFT_MENU
    where MENU_ID = #{id,jdbcType=BIGINT}
  </select>
  <delete id="deleteByPrimaryKey" parameterType="java.lang.Long" >
    delete from LEGOO_LEFT_MENU
    where MENU_ID = #{id,jdbcType=BIGINT}
  </delete>
  <delete id="deleteByExample" parameterType="com.victor.h5blog.entity.LeftMenuExample" >
    delete from LEGOO_LEFT_MENU
    <if test="_parameter != null" >
      <include refid="Example_Where_Clause" />
    </if>
  </delete>
  <insert id="insert" parameterType="com.victor.h5blog.entity.LeftMenu" >
    insert into LEGOO_LEFT_MENU (MENU_ID, MENU_NAME, MENU_URL, 
      MENU_ORDER, MENU_ICO, MENU_STATUS, MENU_PARENT_ID, 
      MENU_KEY)
    values (#{id,jdbcType=BIGINT}, #{name,jdbcType=VARCHAR}, #{url,jdbcType=VARCHAR}, 
      #{order,jdbcType=INTEGER}, #{ico,jdbcType=VARCHAR}, #{status,jdbcType=BIT}, #{parentId,jdbcType=BIGINT}, 
      #{key,jdbcType=VARCHAR})
  </insert>
  <insert id="insertSelective" parameterType="com.victor.h5blog.entity.LeftMenu" >
    insert into LEGOO_LEFT_MENU
    <trim prefix="(" suffix=")" suffixOverrides="," >
      <if test="id != null" >
        MENU_ID,
      </if>
      <if test="name != null" >
        MENU_NAME,
      </if>
      <if test="url != null" >
        MENU_URL,
      </if>
      <if test="order != null" >
        MENU_ORDER,
      </if>
      <if test="ico != null" >
        MENU_ICO,
      </if>
      <if test="status != null" >
        MENU_STATUS,
      </if>
      <if test="parentId != null" >
        MENU_PARENT_ID,
      </if>
      <if test="key != null" >
        MENU_KEY,
      </if>
    </trim>
    <trim prefix="values (" suffix=")" suffixOverrides="," >
      <if test="id != null" >
        #{id,jdbcType=BIGINT},
      </if>
      <if test="name != null" >
        #{name,jdbcType=VARCHAR},
      </if>
      <if test="url != null" >
        #{url,jdbcType=VARCHAR},
      </if>
      <if test="order != null" >
        #{order,jdbcType=INTEGER},
      </if>
      <if test="ico != null" >
        #{ico,jdbcType=VARCHAR},
      </if>
      <if test="status != null" >
        #{status,jdbcType=BIT},
      </if>
      <if test="parentId != null" >
        #{parentId,jdbcType=BIGINT},
      </if>
      <if test="key != null" >
        #{key,jdbcType=VARCHAR},
      </if>
    </trim>
  </insert>
  <select id="countByExample" parameterType="com.victor.h5blog.entity.LeftMenuExample" resultType="java.lang.Integer" >
    select count(*) from LEGOO_LEFT_MENU
    <if test="_parameter != null" >
      <include refid="Example_Where_Clause" />
    </if>
  </select>
  <update id="updateByExampleSelective" parameterType="map" >
    update LEGOO_LEFT_MENU
    <set >
      <if test="record.id != null" >
        MENU_ID = #{record.id,jdbcType=BIGINT},
      </if>
      <if test="record.name != null" >
        MENU_NAME = #{record.name,jdbcType=VARCHAR},
      </if>
      <if test="record.url != null" >
        MENU_URL = #{record.url,jdbcType=VARCHAR},
      </if>
      <if test="record.order != null" >
        MENU_ORDER = #{record.order,jdbcType=INTEGER},
      </if>
      <if test="record.ico != null" >
        MENU_ICO = #{record.ico,jdbcType=VARCHAR},
      </if>
      <if test="record.status != null" >
        MENU_STATUS = #{record.status,jdbcType=BIT},
      </if>
      <if test="record.parentId != null" >
        MENU_PARENT_ID = #{record.parentId,jdbcType=BIGINT},
      </if>
      <if test="record.key != null" >
        MENU_KEY = #{record.key,jdbcType=VARCHAR},
      </if>
    </set>
    <if test="_parameter != null" >
      <include refid="Update_By_Example_Where_Clause" />
    </if>
  </update>
  <update id="updateByExample" parameterType="map" >
    update LEGOO_LEFT_MENU
    set MENU_ID = #{record.id,jdbcType=BIGINT},
      MENU_NAME = #{record.name,jdbcType=VARCHAR},
      MENU_URL = #{record.url,jdbcType=VARCHAR},
      MENU_ORDER = #{record.order,jdbcType=INTEGER},
      MENU_ICO = #{record.ico,jdbcType=VARCHAR},
      MENU_STATUS = #{record.status,jdbcType=BIT},
      MENU_PARENT_ID = #{record.parentId,jdbcType=BIGINT},
      MENU_KEY = #{record.key,jdbcType=VARCHAR}
    <if test="_parameter != null" >
      <include refid="Update_By_Example_Where_Clause" />
    </if>
  </update>
  <update id="updateByPrimaryKeySelective" parameterType="com.victor.h5blog.entity.LeftMenu" >
    update LEGOO_LEFT_MENU
    <set >
      <if test="name != null" >
        MENU_NAME = #{name,jdbcType=VARCHAR},
      </if>
      <if test="url != null" >
        MENU_URL = #{url,jdbcType=VARCHAR},
      </if>
      <if test="order != null" >
        MENU_ORDER = #{order,jdbcType=INTEGER},
      </if>
      <if test="ico != null" >
        MENU_ICO = #{ico,jdbcType=VARCHAR},
      </if>
      <if test="status != null" >
        MENU_STATUS = #{status,jdbcType=BIT},
      </if>
      <if test="parentId != null" >
        MENU_PARENT_ID = #{parentId,jdbcType=BIGINT},
      </if>
      <if test="key != null" >
        MENU_KEY = #{key,jdbcType=VARCHAR},
      </if>
    </set>
    where MENU_ID = #{id,jdbcType=BIGINT}
  </update>
  <update id="updateByPrimaryKey" parameterType="com.victor.h5blog.entity.LeftMenu" >
    update LEGOO_LEFT_MENU
    set MENU_NAME = #{name,jdbcType=VARCHAR},
      MENU_URL = #{url,jdbcType=VARCHAR},
      MENU_ORDER = #{order,jdbcType=INTEGER},
      MENU_ICO = #{ico,jdbcType=VARCHAR},
      MENU_STATUS = #{status,jdbcType=BIT},
      MENU_PARENT_ID = #{parentId,jdbcType=BIGINT},
      MENU_KEY = #{key,jdbcType=VARCHAR}
    where MENU_ID = #{id,jdbcType=BIGINT}
  </update>
</mapper>